{
    "os": "Linux-5.4.0-155-generic-x86_64-with-glibc2.17",
    "python": "3.8.10",
    "heartbeatAt": "2025-04-04T03:42:25.200436",
    "startedAt": "2025-04-04T03:42:22.532355",
    "docker": null,
    "cuda": null,
    "args": [
        "outputs/experiments/seq-training-doc-id-repeat-subset_pretrain/train_config.yaml"
    ],
    "state": "running",
    "program": "train.py",
    "codePathLocal": "train.py",
    "codePath": "train.py",
    "host": "autodl-container-11d445a847-7722b670",
    "username": "root",
    "executable": "/root/miniconda3/bin/python",
    "cpu_count": 64,
    "cpu_count_logical": 128,
    "cpu_freq": {
        "current": 1033.9213515625001,
        "min": 800.0,
        "max": 2001.0
    },
    "cpu_freq_per_core": [
        {
            "current": 900.0,
            "min": 800.0,
            "max": 2001.0
        },
        {
            "current": 800.99,
            "min": 800.0,
            "max": 2001.0
        },
        {
            "current": 800.0,
            "min": 800.0,
            "max": 2001.0
        },
        {
            "current": 1560.414,
            "min": 800.0,
            "max": 2001.0
        },
        {
            "current": 801.554,
            "min": 800.0,
            "max": 2001.0
        },
        {
            "current": 863.133,
            "min": 800.0,
            "max": 2001.0
        },
        {
            "current": 799.904,
            "min": 800.0,
            "max": 2001.0
        },
        {
            "current": 800.03,
            "min": 800.0,
            "max": 2001.0
        },
        {
            "current": 799.154,
            "min": 800.0,
            "max": 2001.0
        },
        {
            "current": 800.0,
            "min": 800.0,
            "max": 2001.0
        },
        {
            "current": 2000.0,
            "min": 800.0,
            "max": 2001.0
        },
        {
            "current": 800.0,
            "min": 800.0,
            "max": 2001.0
        },
        {
            "current": 800.0,
            "min": 800.0,
            "max": 2001.0
        },
        {
            "current": 2000.0,
            "min": 800.0,
            "max": 2001.0
        },
        {
            "current": 800.0,
            "min": 800.0,
            "max": 2001.0
        },
        {
            "current": 800.537,
            "min": 800.0,
            "max": 2001.0
        },
        {
            "current": 991.852,
            "min": 800.0,
            "max": 2001.0
        },
        {
            "current": 811.827,
            "min": 800.0,
            "max": 2001.0
        },
        {
            "current": 800.0,
            "min": 800.0,
            "max": 2001.0
        },
        {
            "current": 799.973,
            "min": 800.0,
            "max": 2001.0
        },
        {
            "current": 2442.474,
            "min": 800.0,
            "max": 2001.0
        },
        {
            "current": 2672.712,
            "min": 800.0,
            "max": 2001.0
        },
        {
            "current": 800.0,
            "min": 800.0,
            "max": 2001.0
        },
        {
            "current": 801.04,
            "min": 800.0,
            "max": 2001.0
        },
        {
            "current": 800.0,
            "min": 800.0,
            "max": 2001.0
        },
        {
            "current": 800.0,
            "min": 800.0,
            "max": 2001.0
        },
        {
            "current": 800.146,
            "min": 800.0,
            "max": 2001.0
        },
        {
            "current": 900.0,
            "min": 800.0,
            "max": 2001.0
        },
        {
            "current": 1046.791,
            "min": 800.0,
            "max": 2001.0
        },
        {
            "current": 800.388,
            "min": 800.0,
            "max": 2001.0
        },
        {
            "current": 800.681,
            "min": 800.0,
            "max": 2001.0
        },
        {
            "current": 800.0,
            "min": 800.0,
            "max": 2001.0
        },
        {
            "current": 798.965,
            "min": 800.0,
            "max": 2001.0
        },
        {
            "current": 1298.581,
            "min": 800.0,
            "max": 2001.0
        },
        {
            "current": 1715.146,
            "min": 800.0,
            "max": 2001.0
        },
        {
            "current": 800.0,
            "min": 800.0,
            "max": 2001.0
        },
        {
            "current": 800.0,
            "min": 800.0,
            "max": 2001.0
        },
        {
            "current": 1345.559,
            "min": 800.0,
            "max": 2001.0
        },
        {
            "current": 1244.148,
            "min": 800.0,
            "max": 2001.0
        },
        {
            "current": 801.808,
            "min": 800.0,
            "max": 2001.0
        },
        {
            "current": 1063.22,
            "min": 800.0,
            "max": 2001.0
        },
        {
            "current": 799.93,
            "min": 800.0,
            "max": 2001.0
        },
        {
            "current": 800.698,
            "min": 800.0,
            "max": 2001.0
        },
        {
            "current": 800.0,
            "min": 800.0,
            "max": 2001.0
        },
        {
            "current": 802.42,
            "min": 800.0,
            "max": 2001.0
        },
        {
            "current": 800.0,
            "min": 800.0,
            "max": 2001.0
        },
        {
            "current": 799.312,
            "min": 800.0,
            "max": 2001.0
        },
        {
            "current": 840.629,
            "min": 800.0,
            "max": 2001.0
        },
        {
            "current": 819.667,
            "min": 800.0,
            "max": 2001.0
        },
        {
            "current": 1014.663,
            "min": 800.0,
            "max": 2001.0
        },
        {
            "current": 800.0,
            "min": 800.0,
            "max": 2001.0
        },
        {
            "current": 1759.865,
            "min": 800.0,
            "max": 2001.0
        },
        {
            "current": 800.74,
            "min": 800.0,
            "max": 2001.0
        },
        {
            "current": 916.287,
            "min": 800.0,
            "max": 2001.0
        },
        {
            "current": 1701.82,
            "min": 800.0,
            "max": 2001.0
        },
        {
            "current": 830.589,
            "min": 800.0,
            "max": 2001.0
        },
        {
            "current": 1999.998,
            "min": 800.0,
            "max": 2001.0
        },
        {
            "current": 877.905,
            "min": 800.0,
            "max": 2001.0
        },
        {
            "current": 799.791,
            "min": 800.0,
            "max": 2001.0
        },
        {
            "current": 2432.72,
            "min": 800.0,
            "max": 2001.0
        },
        {
            "current": 800.042,
            "min": 800.0,
            "max": 2001.0
        },
        {
            "current": 852.14,
            "min": 800.0,
            "max": 2001.0
        },
        {
            "current": 880.371,
            "min": 800.0,
            "max": 2001.0
        },
        {
            "current": 801.292,
            "min": 800.0,
            "max": 2001.0
        },
        {
            "current": 900.0,
            "min": 800.0,
            "max": 2001.0
        },
        {
            "current": 800.0,
            "min": 800.0,
            "max": 2001.0
        },
        {
            "current": 800.0,
            "min": 800.0,
            "max": 2001.0
        },
        {
            "current": 799.923,
            "min": 800.0,
            "max": 2001.0
        },
        {
            "current": 801.281,
            "min": 800.0,
            "max": 2001.0
        },
        {
            "current": 848.071,
            "min": 800.0,
            "max": 2001.0
        },
        {
            "current": 799.938,
            "min": 800.0,
            "max": 2001.0
        },
        {
            "current": 798.997,
            "min": 800.0,
            "max": 2001.0
        },
        {
            "current": 800.0,
            "min": 800.0,
            "max": 2001.0
        },
        {
            "current": 801.448,
            "min": 800.0,
            "max": 2001.0
        },
        {
            "current": 2000.0,
            "min": 800.0,
            "max": 2001.0
        },
        {
            "current": 800.0,
            "min": 800.0,
            "max": 2001.0
        },
        {
            "current": 799.951,
            "min": 800.0,
            "max": 2001.0
        },
        {
            "current": 1997.518,
            "min": 800.0,
            "max": 2001.0
        },
        {
            "current": 799.062,
            "min": 800.0,
            "max": 2001.0
        },
        {
            "current": 800.409,
            "min": 800.0,
            "max": 2001.0
        },
        {
            "current": 932.585,
            "min": 800.0,
            "max": 2001.0
        },
        {
            "current": 799.015,
            "min": 800.0,
            "max": 2001.0
        },
        {
            "current": 799.949,
            "min": 800.0,
            "max": 2001.0
        },
        {
            "current": 800.0,
            "min": 800.0,
            "max": 2001.0
        },
        {
            "current": 2396.689,
            "min": 800.0,
            "max": 2001.0
        },
        {
            "current": 2434.937,
            "min": 800.0,
            "max": 2001.0
        },
        {
            "current": 800.0,
            "min": 800.0,
            "max": 2001.0
        },
        {
            "current": 801.071,
            "min": 800.0,
            "max": 2001.0
        },
        {
            "current": 800.0,
            "min": 800.0,
            "max": 2001.0
        },
        {
            "current": 800.0,
            "min": 800.0,
            "max": 2001.0
        },
        {
            "current": 800.582,
            "min": 800.0,
            "max": 2001.0
        },
        {
            "current": 853.985,
            "min": 800.0,
            "max": 2001.0
        },
        {
            "current": 1100.817,
            "min": 800.0,
            "max": 2001.0
        },
        {
            "current": 800.754,
            "min": 800.0,
            "max": 2001.0
        },
        {
            "current": 800.715,
            "min": 800.0,
            "max": 2001.0
        },
        {
            "current": 800.0,
            "min": 800.0,
            "max": 2001.0
        },
        {
            "current": 799.895,
            "min": 800.0,
            "max": 2001.0
        },
        {
            "current": 865.441,
            "min": 800.0,
            "max": 2001.0
        },
        {
            "current": 2001.651,
            "min": 800.0,
            "max": 2001.0
        },
        {
            "current": 1174.711,
            "min": 800.0,
            "max": 2001.0
        },
        {
            "current": 800.0,
            "min": 800.0,
            "max": 2001.0
        },
        {
            "current": 2001.497,
            "min": 800.0,
            "max": 2001.0
        },
        {
            "current": 1478.712,
            "min": 800.0,
            "max": 2001.0
        },
        {
            "current": 800.106,
            "min": 800.0,
            "max": 2001.0
        },
        {
            "current": 870.98,
            "min": 800.0,
            "max": 2001.0
        },
        {
            "current": 800.0,
            "min": 800.0,
            "max": 2001.0
        },
        {
            "current": 800.121,
            "min": 800.0,
            "max": 2001.0
        },
        {
            "current": 2000.0,
            "min": 800.0,
            "max": 2001.0
        },
        {
            "current": 799.93,
            "min": 800.0,
            "max": 2001.0
        },
        {
            "current": 806.796,
            "min": 800.0,
            "max": 2001.0
        },
        {
            "current": 800.0,
            "min": 800.0,
            "max": 2001.0
        },
        {
            "current": 800.0,
            "min": 800.0,
            "max": 2001.0
        },
        {
            "current": 799.004,
            "min": 800.0,
            "max": 2001.0
        },
        {
            "current": 800.0,
            "min": 800.0,
            "max": 2001.0
        },
        {
            "current": 817.413,
            "min": 800.0,
            "max": 2001.0
        },
        {
            "current": 799.041,
            "min": 800.0,
            "max": 2001.0
        },
        {
            "current": 801.019,
            "min": 800.0,
            "max": 2001.0
        },
        {
            "current": 1943.14,
            "min": 800.0,
            "max": 2001.0
        },
        {
            "current": 800.997,
            "min": 800.0,
            "max": 2001.0
        },
        {
            "current": 941.48,
            "min": 800.0,
            "max": 2001.0
        },
        {
            "current": 2000.097,
            "min": 800.0,
            "max": 2001.0
        },
        {
            "current": 1027.675,
            "min": 800.0,
            "max": 2001.0
        },
        {
            "current": 800.077,
            "min": 800.0,
            "max": 2001.0
        },
        {
            "current": 2421.143,
            "min": 800.0,
            "max": 2001.0
        },
        {
            "current": 800.16,
            "min": 800.0,
            "max": 2001.0
        },
        {
            "current": 800.0,
            "min": 800.0,
            "max": 2001.0
        },
        {
            "current": 1026.733,
            "min": 800.0,
            "max": 2001.0
        },
        {
            "current": 801.343,
            "min": 800.0,
            "max": 2001.0
        }
    ],
    "disk": {
        "/": {
            "total": 30.0,
            "used": 9.762657165527344
        }
    },
    "gpu": "NVIDIA vGPU-32GB",
    "gpu_count": 1,
    "gpu_devices": [
        {
            "name": "NVIDIA vGPU-32GB",
            "memory_total": 34351349760
        }
    ],
    "memory": {
        "total": 1007.5241508483887
    }
}
