{
    "os": "Linux-5.4.0-155-generic-x86_64-with-glibc2.17",
    "python": "3.8.10",
    "heartbeatAt": "2025-04-01T12:05:48.433118",
    "startedAt": "2025-04-01T12:05:48.237710",
    "docker": null,
    "cuda": null,
    "args": [
        "outputs/experiments/seq-training-doc-id-repeat-subset_pretrain/train_config.yaml"
    ],
    "state": "running",
    "program": "train.py",
    "codePathLocal": "train.py",
    "codePath": "train.py",
    "host": "autodl-container-11d445a847-7722b670",
    "username": "root",
    "executable": "/root/miniconda3/bin/python",
    "cpu_count": 64,
    "cpu_count_logical": 128,
    "cpu_freq": {
        "current": 860.5716796874999,
        "min": 800.0,
        "max": 2001.0
    },
    "cpu_freq_per_core": [
        {
            "current": 874.101,
            "min": 800.0,
            "max": 2001.0
        },
        {
            "current": 800.185,
            "min": 800.0,
            "max": 2001.0
        },
        {
            "current": 803.336,
            "min": 800.0,
            "max": 2001.0
        },
        {
            "current": 810.024,
            "min": 800.0,
            "max": 2001.0
        },
        {
            "current": 800.388,
            "min": 800.0,
            "max": 2001.0
        },
        {
            "current": 800.276,
            "min": 800.0,
            "max": 2001.0
        },
        {
            "current": 801.18,
            "min": 800.0,
            "max": 2001.0
        },
        {
            "current": 800.343,
            "min": 800.0,
            "max": 2001.0
        },
        {
            "current": 801.182,
            "min": 800.0,
            "max": 2001.0
        },
        {
            "current": 800.178,
            "min": 800.0,
            "max": 2001.0
        },
        {
            "current": 800.16,
            "min": 800.0,
            "max": 2001.0
        },
        {
            "current": 852.115,
            "min": 800.0,
            "max": 2001.0
        },
        {
            "current": 801.185,
            "min": 800.0,
            "max": 2001.0
        },
        {
            "current": 800.16,
            "min": 800.0,
            "max": 2001.0
        },
        {
            "current": 800.143,
            "min": 800.0,
            "max": 2001.0
        },
        {
            "current": 800.136,
            "min": 800.0,
            "max": 2001.0
        },
        {
            "current": 800.14,
            "min": 800.0,
            "max": 2001.0
        },
        {
            "current": 800.273,
            "min": 800.0,
            "max": 2001.0
        },
        {
            "current": 800.198,
            "min": 800.0,
            "max": 2001.0
        },
        {
            "current": 811.889,
            "min": 800.0,
            "max": 2001.0
        },
        {
            "current": 800.752,
            "min": 800.0,
            "max": 2001.0
        },
        {
            "current": 801.32,
            "min": 800.0,
            "max": 2001.0
        },
        {
            "current": 892.655,
            "min": 800.0,
            "max": 2001.0
        },
        {
            "current": 834.284,
            "min": 800.0,
            "max": 2001.0
        },
        {
            "current": 800.116,
            "min": 800.0,
            "max": 2001.0
        },
        {
            "current": 920.79,
            "min": 800.0,
            "max": 2001.0
        },
        {
            "current": 820.932,
            "min": 800.0,
            "max": 2001.0
        },
        {
            "current": 800.175,
            "min": 800.0,
            "max": 2001.0
        },
        {
            "current": 880.006,
            "min": 800.0,
            "max": 2001.0
        },
        {
            "current": 801.147,
            "min": 800.0,
            "max": 2001.0
        },
        {
            "current": 800.111,
            "min": 800.0,
            "max": 2001.0
        },
        {
            "current": 800.033,
            "min": 800.0,
            "max": 2001.0
        },
        {
            "current": 800.876,
            "min": 800.0,
            "max": 2001.0
        },
        {
            "current": 800.742,
            "min": 800.0,
            "max": 2001.0
        },
        {
            "current": 800.031,
            "min": 800.0,
            "max": 2001.0
        },
        {
            "current": 807.344,
            "min": 800.0,
            "max": 2001.0
        },
        {
            "current": 800.075,
            "min": 800.0,
            "max": 2001.0
        },
        {
            "current": 800.364,
            "min": 800.0,
            "max": 2001.0
        },
        {
            "current": 2000.0,
            "min": 800.0,
            "max": 2001.0
        },
        {
            "current": 801.557,
            "min": 800.0,
            "max": 2001.0
        },
        {
            "current": 800.165,
            "min": 800.0,
            "max": 2001.0
        },
        {
            "current": 1077.134,
            "min": 800.0,
            "max": 2001.0
        },
        {
            "current": 800.366,
            "min": 800.0,
            "max": 2001.0
        },
        {
            "current": 800.0,
            "min": 800.0,
            "max": 2001.0
        },
        {
            "current": 800.385,
            "min": 800.0,
            "max": 2001.0
        },
        {
            "current": 801.003,
            "min": 800.0,
            "max": 2001.0
        },
        {
            "current": 808.728,
            "min": 800.0,
            "max": 2001.0
        },
        {
            "current": 881.395,
            "min": 800.0,
            "max": 2001.0
        },
        {
            "current": 801.28,
            "min": 800.0,
            "max": 2001.0
        },
        {
            "current": 800.033,
            "min": 800.0,
            "max": 2001.0
        },
        {
            "current": 800.719,
            "min": 800.0,
            "max": 2001.0
        },
        {
            "current": 800.093,
            "min": 800.0,
            "max": 2001.0
        },
        {
            "current": 849.678,
            "min": 800.0,
            "max": 2001.0
        },
        {
            "current": 800.286,
            "min": 800.0,
            "max": 2001.0
        },
        {
            "current": 800.309,
            "min": 800.0,
            "max": 2001.0
        },
        {
            "current": 801.188,
            "min": 800.0,
            "max": 2001.0
        },
        {
            "current": 800.76,
            "min": 800.0,
            "max": 2001.0
        },
        {
            "current": 800.745,
            "min": 800.0,
            "max": 2001.0
        },
        {
            "current": 800.774,
            "min": 800.0,
            "max": 2001.0
        },
        {
            "current": 801.162,
            "min": 800.0,
            "max": 2001.0
        },
        {
            "current": 800.031,
            "min": 800.0,
            "max": 2001.0
        },
        {
            "current": 898.081,
            "min": 800.0,
            "max": 2001.0
        },
        {
            "current": 800.746,
            "min": 800.0,
            "max": 2001.0
        },
        {
            "current": 800.361,
            "min": 800.0,
            "max": 2001.0
        },
        {
            "current": 800.39,
            "min": 800.0,
            "max": 2001.0
        },
        {
            "current": 800.183,
            "min": 800.0,
            "max": 2001.0
        },
        {
            "current": 801.156,
            "min": 800.0,
            "max": 2001.0
        },
        {
            "current": 806.377,
            "min": 800.0,
            "max": 2001.0
        },
        {
            "current": 800.215,
            "min": 800.0,
            "max": 2001.0
        },
        {
            "current": 801.166,
            "min": 800.0,
            "max": 2001.0
        },
        {
            "current": 800.308,
            "min": 800.0,
            "max": 2001.0
        },
        {
            "current": 800.144,
            "min": 800.0,
            "max": 2001.0
        },
        {
            "current": 800.386,
            "min": 800.0,
            "max": 2001.0
        },
        {
            "current": 800.106,
            "min": 800.0,
            "max": 2001.0
        },
        {
            "current": 800.183,
            "min": 800.0,
            "max": 2001.0
        },
        {
            "current": 823.256,
            "min": 800.0,
            "max": 2001.0
        },
        {
            "current": 800.139,
            "min": 800.0,
            "max": 2001.0
        },
        {
            "current": 800.808,
            "min": 800.0,
            "max": 2001.0
        },
        {
            "current": 800.071,
            "min": 800.0,
            "max": 2001.0
        },
        {
            "current": 801.172,
            "min": 800.0,
            "max": 2001.0
        },
        {
            "current": 800.047,
            "min": 800.0,
            "max": 2001.0
        },
        {
            "current": 801.438,
            "min": 800.0,
            "max": 2001.0
        },
        {
            "current": 800.579,
            "min": 800.0,
            "max": 2001.0
        },
        {
            "current": 800.791,
            "min": 800.0,
            "max": 2001.0
        },
        {
            "current": 801.118,
            "min": 800.0,
            "max": 2001.0
        },
        {
            "current": 800.196,
            "min": 800.0,
            "max": 2001.0
        },
        {
            "current": 847.834,
            "min": 800.0,
            "max": 2001.0
        },
        {
            "current": 848.841,
            "min": 800.0,
            "max": 2001.0
        },
        {
            "current": 801.513,
            "min": 800.0,
            "max": 2001.0
        },
        {
            "current": 983.808,
            "min": 800.0,
            "max": 2001.0
        },
        {
            "current": 967.061,
            "min": 800.0,
            "max": 2001.0
        },
        {
            "current": 801.198,
            "min": 800.0,
            "max": 2001.0
        },
        {
            "current": 1001.117,
            "min": 800.0,
            "max": 2001.0
        },
        {
            "current": 1001.667,
            "min": 800.0,
            "max": 2001.0
        },
        {
            "current": 801.169,
            "min": 800.0,
            "max": 2001.0
        },
        {
            "current": 800.757,
            "min": 800.0,
            "max": 2001.0
        },
        {
            "current": 800.223,
            "min": 800.0,
            "max": 2001.0
        },
        {
            "current": 801.139,
            "min": 800.0,
            "max": 2001.0
        },
        {
            "current": 801.167,
            "min": 800.0,
            "max": 2001.0
        },
        {
            "current": 1000.57,
            "min": 800.0,
            "max": 2001.0
        },
        {
            "current": 801.135,
            "min": 800.0,
            "max": 2001.0
        },
        {
            "current": 800.39,
            "min": 800.0,
            "max": 2001.0
        },
        {
            "current": 2000.0,
            "min": 800.0,
            "max": 2001.0
        },
        {
            "current": 800.293,
            "min": 800.0,
            "max": 2001.0
        },
        {
            "current": 800.286,
            "min": 800.0,
            "max": 2001.0
        },
        {
            "current": 934.548,
            "min": 800.0,
            "max": 2001.0
        },
        {
            "current": 800.225,
            "min": 800.0,
            "max": 2001.0
        },
        {
            "current": 800.169,
            "min": 800.0,
            "max": 2001.0
        },
        {
            "current": 800.386,
            "min": 800.0,
            "max": 2001.0
        },
        {
            "current": 800.798,
            "min": 800.0,
            "max": 2001.0
        },
        {
            "current": 801.142,
            "min": 800.0,
            "max": 2001.0
        },
        {
            "current": 876.231,
            "min": 800.0,
            "max": 2001.0
        },
        {
            "current": 800.072,
            "min": 800.0,
            "max": 2001.0
        },
        {
            "current": 800.095,
            "min": 800.0,
            "max": 2001.0
        },
        {
            "current": 801.094,
            "min": 800.0,
            "max": 2001.0
        },
        {
            "current": 800.134,
            "min": 800.0,
            "max": 2001.0
        },
        {
            "current": 841.032,
            "min": 800.0,
            "max": 2001.0
        },
        {
            "current": 800.801,
            "min": 800.0,
            "max": 2001.0
        },
        {
            "current": 800.284,
            "min": 800.0,
            "max": 2001.0
        },
        {
            "current": 800.325,
            "min": 800.0,
            "max": 2001.0
        },
        {
            "current": 800.245,
            "min": 800.0,
            "max": 2001.0
        },
        {
            "current": 800.775,
            "min": 800.0,
            "max": 2001.0
        },
        {
            "current": 800.765,
            "min": 800.0,
            "max": 2001.0
        },
        {
            "current": 801.178,
            "min": 800.0,
            "max": 2001.0
        },
        {
            "current": 801.177,
            "min": 800.0,
            "max": 2001.0
        },
        {
            "current": 900.936,
            "min": 800.0,
            "max": 2001.0
        },
        {
            "current": 801.509,
            "min": 800.0,
            "max": 2001.0
        },
        {
            "current": 800.762,
            "min": 800.0,
            "max": 2001.0
        }
    ],
    "disk": {
        "/": {
            "total": 30.0,
            "used": 9.719684600830078
        }
    },
    "gpu": "NVIDIA vGPU-32GB",
    "gpu_count": 1,
    "gpu_devices": [
        {
            "name": "NVIDIA vGPU-32GB",
            "memory_total": 34351349760
        }
    ],
    "memory": {
        "total": 1007.5241508483887
    }
}
